sqlmodelgenerator/__init__.py
sqlmodelgenerator/__main__.py
sqlmodelgenerator/cli.py
sqlmodelgenerator/config.py
sqlmodelgenerator/generate.py
sqlmodelgenerator/introspect.py
sqlmodelgenerator/templates/__init__.py
sqlmodelgenerator-0.1.0.dist-info/licenses/LICENSE
sqlmodelgenerator-0.1.0.dist-info/METADATA
sqlmodelgenerator-0.1.0.dist-info/WHEEL
sqlmodelgenerator-0.1.0.dist-info/entry_points.txt
sqlmodelgenerator-0.1.0.dist-info/top_level.txt
sqlmodelgenerator-0.1.0.dist-info/RECORD
