Metadata-Version: 2.4
Name: sqlmodelgenerator
Version: 0.1.0
Summary: CLI tool to generate SQLModel models from a Postgres database via SQLAlchemy introspection.
Author-email: "Finatic.dev" <support@finatic.dev>
License-Expression: MIT
Project-URL: Homepage, https://github.com/finaticdev/sqlmodelgenerator
Classifier: Programming Language :: Python :: 3
Classifier: Operating System :: OS Independent
Requires-Python: >=3.10
License-File: LICENSE
Requires-Dist: sqlmodel>=0.0.8
Requires-Dist: sqlalchemy>=2.0.0
Requires-Dist: psycopg2-binary>=2.9.0
Requires-Dist: typer>=0.15.1
Requires-Dist: jinja2>=3.0.0
Requires-Dist: PyYAML>=6.0
Requires-Dist: click==8.1.7
Provides-Extra: dev
Requires-Dist: pytest>=7.0.0; extra == "dev"
Requires-Dist: pytest-cov>=4.0.0; extra == "dev"
Requires-Dist: flake8>=6.0.0; extra == "dev"
Requires-Dist: mypy>=1.0.0; extra == "dev"
Requires-Dist: black>=23.0.0; extra == "dev"
Requires-Dist: typer>=0.15.1; extra == "dev"
Requires-Dist: click==8.1.7; extra == "dev"
Dynamic: license-file
